{
	"id": "ready-set-roll-for-5e-player-version",
	"title": "Ready Set Roll for 5e - Player version",
	"version": "3.4.2",
	"compatibility": {
		"minimum": "12",
		"verified": "12"
	},
	"authors": [
		{
			"name": "MangoFVTT",
			"discord": "MangoFVTT"
		},
		{
			"name": "SPancerfaustyna",
			"discord": "kitsune_sister",
			"flags": {}
		}
	],
	"esmodules": [
		"./src/ready-set-roll.js",
		"./src/module/config.js"
	],
	"styles": [
		"./css/ready-set-roll.css"
	],
	"languages": [
		{
			"lang": "en",
			"name": "English",
			"path": "lang/en.json"
		},
		{
			"lang": "pt-BR",
			"name": "Português (Brasil)",
			"path": "lang/pt-BR.json"
		}
	],
	"relationships": {
		"requires": [
			{
				"id": "socketlib",
				"type": "module",
				"compatibility": {}
			}
		],
		"systems": [
			{
				"id": "dnd5e",
				"type": "system",
				"compatibility": {}
			}
		]
	},
	"url": "https://github.com/SPancerfaustyna/fvtt-ready-set-roll-5e-player-version",
	"manifest": "https://github.com/SPancerfaustyna/fvtt-ready-set-roll-5e-player-version/master/module.json",
	"download": "https://github.com/SPancerfaustyna/fvtt-ready-set-roll-5e-player-version/releases/download/release-3.4.2/rsr5e-release-3.4.2.zip",
	"bugs": "https://github.com/SPancerfaustyna/fvtt-ready-set-roll-5e-player-version/issues",
	"readme": "https://github.com/SPancerfaustyna/fvtt-ready-set-roll-5e-player-version/blob/master/README.md"
}
